mynathon/__init__.py
mynathon/__main__.py
mynathon/mynathon.py
mynathon-0.1.2.data/scripts/mynathon
mynathon-0.1.2.dist-info/METADATA
mynathon-0.1.2.dist-info/WHEEL
mynathon-0.1.2.dist-info/entry_points.txt
mynathon-0.1.2.dist-info/top_level.txt
mynathon-0.1.2.dist-info/RECORD
