Metadata-Version: 2.1
Name: mynathon
Version: 0.1.2
Summary: Mynathon - Езикът за майни и маняци.
Home-page: https://github.com/allexks/mynathon
Author: Alexander Ignatov
Author-email: yalishanda@abv.bg
License: MIT
Download-URL: https://github.com/allexks/mynathon/archive/0.1.2.tar.gz
Keywords: maina,manqk,bg,stoyan kolev,jargon
Platform: UNKNOWN
Classifier: Intended Audience :: Developers
Classifier: Topic :: Software Development :: Build Tools
Classifier: License :: OSI Approved :: MIT License
Classifier: Programming Language :: Python :: 3
Classifier: Programming Language :: Python :: 3.4
Classifier: Programming Language :: Python :: 3.5
Classifier: Programming Language :: Python :: 3.6
Classifier: Programming Language :: Python :: 3.7
Classifier: Programming Language :: Python :: 3.8
